{"cameraMode":{"drawMode":0,"name":"Shaded","section":"Shading Mode"},"sceneLighting":true,"audioPlay":false,"sceneViewState":{"m_AlwaysRefresh":false,"showFog":true,"showSkybox":true,"showFlares":true,"showImageEffects":true,"showParticleSystems":true,"showVisualEffectGraphs":true,"m_FxEnabled":true},"in2DMode":false,"pivot":{"x":4.428131103515625,"y":6.501023292541504,"z":-9.727804183959961},"rotation":{"x":-0.15093174576759339,"y":0.07860780507326126,"z":-0.011944343335926533,"w":-0.9852685332298279},"size":0.9323969483375549,"orthographic":false}